fujielab/asr/espnet_ext/espnet2/__init__.py
fujielab/asr/espnet_ext/espnet2/asr/__init__.py
fujielab/asr/espnet_ext/espnet2/asr/beam_search_transducer_online.py
fujielab/asr/espnet_ext/espnet2/asr/frontend/__init__.py
fujielab/asr/espnet_ext/espnet2/asr/frontend/online_audio_processor.py
fujielab/asr/espnet_ext/espnet2/bin/__init__.py
fujielab/asr/espnet_ext/espnet2/bin/asr_transducer_inference_cbs.py
fujielab_asr-0.1.3.dist-info/licenses/LICENSE
warprnnt_pytorch/__init__.py
warprnnt_pytorch/warprnnt_pytorch.py
fujielab_asr-0.1.3.dist-info/METADATA
fujielab_asr-0.1.3.dist-info/WHEEL
fujielab_asr-0.1.3.dist-info/top_level.txt
fujielab_asr-0.1.3.dist-info/RECORD
