Metadata-Version: 2.4
Name: fujielab-asr
Version: 0.1.3
Summary: Automatic Speech Recognition (ASR) tools for Fujie Lab
Author-email: Shinya Fujie <shinya.fujie@p.chibakoudai.jp>
License:                                  Apache License
Project-URL: homepage, https://github.com/fujielab/fujielab-asr
Requires-Python: <3.12,>=3.10
License-File: LICENSE
Requires-Dist: espnet>=202301
Requires-Dist: espnet_model_zoo
Requires-Dist: torchaudio
Requires-Dist: typeguard==2.13.3
Dynamic: license-file
